gradio_url_buttons/__init__.py
gradio_url_buttons/source_buttons.py
gradio_url_buttons/source_buttons.pyi
gradio_url_buttons/templates/component/index.js
gradio_url_buttons/templates/component/style.css
gradio_url_buttons/templates/example/index.js
gradio_url_buttons/templates/example/style.css
gradio_url_buttons-0.0.2.dist-info/METADATA
gradio_url_buttons-0.0.2.dist-info/WHEEL
gradio_url_buttons-0.0.2.dist-info/RECORD
